UoMConversion/__init__.py
UoMConversion/convert.py
UoMConversion-0.1.0.dist-info/METADATA
UoMConversion-0.1.0.dist-info/WHEEL
UoMConversion-0.1.0.dist-info/top_level.txt
UoMConversion-0.1.0.dist-info/RECORD
