Metadata-Version: 2.1
Name: UoMConversion
Version: 0.1.0
Summary: My first Python library for conversion of UOM
Author: rohan_ajila
